README.md
esqlite.py
setup.py
esqlite.egg-info/PKG-INFO
esqlite.egg-info/SOURCES.txt
esqlite.egg-info/dependency_links.txt
esqlite.egg-info/top_level.txt