Metadata-Version: 2.1
Name: esqlite
Version: 0.0.1
Summary: esqlite means 'easy sqlite', is a sqlite3 wrapper.
Home-page: https://gitee.com/lixkhao/esqlite
Author: Li Xiangkui
Author-email: 1749498702@qq.com
License: MIT Licence
Keywords: pip,esqlite
Platform: any
